{
	"params": [
		{
			"units_per_layer": [
				4,
				1
			],
			"acts": [
				"leaky_relu",
				"tanh"
			],
			"init_type": "uniform",
			"lower_lim": -0.1,
			"upper_lim": 0.1,
			"momentum": 0.7,
			"batch_size": "full",
			"lr": 0.1,
			"loss": "squared",
			"metr": "bin_class_acc",
			"epochs": 50
		},
		{
			"units_per_layer": [
				4,
				1
			],
			"acts": [
				"leaky_relu",
				"tanh"
			],
			"init_type": "uniform",
			"lower_lim": -0.1,
			"upper_lim": 0.1,
			"momentum": 0.7,
			"batch_size": "full",
			"lr": 0.1,
			"loss": "squared",
			"metr": "bin_class_acc",
			"epochs": 100
		},
		{
			"units_per_layer": [
				4,
				1
			],
			"acts": [
				"leaky_relu",
				"tanh"
			],
			"init_type": "uniform",
			"lower_lim": -0.1,
			"upper_lim": 0.1,
			"momentum": 0.7,
			"batch_size": "full",
			"lr": 0.1,
			"loss": "squared",
			"metr": "bin_class_acc",
			"epochs": 150
		},
		{
			"units_per_layer": [
				4,
				1
			],
			"acts": [
				"leaky_relu",
				"tanh"
			],
			"init_type": "uniform",
			"lower_lim": -0.1,
			"upper_lim": 0.1,
			"momentum": 0.7,
			"batch_size": "full",
			"lr": 0.3,
			"loss": "squared",
			"metr": "bin_class_acc",
			"epochs": 50
		},
		{
			"units_per_layer": [
				4,
				1
			],
			"acts": [
				"leaky_relu",
				"tanh"
			],
			"init_type": "uniform",
			"lower_lim": -0.1,
			"upper_lim": 0.1,
			"momentum": 0.7,
			"batch_size": "full",
			"lr": 0.3,
			"loss": "squared",
			"metr": "bin_class_acc",
			"epochs": 100
		},
		{
			"units_per_layer": [
				4,
				1
			],
			"acts": [
				"leaky_relu",
				"tanh"
			],
			"init_type": "uniform",
			"lower_lim": -0.1,
			"upper_lim": 0.1,
			"momentum": 0.7,
			"batch_size": "full",
			"lr": 0.3,
			"loss": "squared",
			"metr": "bin_class_acc",
			"epochs": 150
		},
		{
			"units_per_layer": [
				2,
				2,
				1
			],
			"acts": [
				"leaky_relu",
				"leaky_relu",
				"tanh"
			],
			"init_type": "uniform",
			"lower_lim": -0.1,
			"upper_lim": 0.1,
			"momentum": 0.7,
			"batch_size": "full",
			"lr": 0.1,
			"loss": "squared",
			"metr": "bin_class_acc",
			"epochs": 50
		},
		{
			"units_per_layer": [
				2,
				2,
				1
			],
			"acts": [
				"leaky_relu",
				"leaky_relu",
				"tanh"
			],
			"init_type": "uniform",
			"lower_lim": -0.1,
			"upper_lim": 0.1,
			"momentum": 0.7,
			"batch_size": "full",
			"lr": 0.1,
			"loss": "squared",
			"metr": "bin_class_acc",
			"epochs": 100
		},
		{
			"units_per_layer": [
				2,
				2,
				1
			],
			"acts": [
				"leaky_relu",
				"leaky_relu",
				"tanh"
			],
			"init_type": "uniform",
			"lower_lim": -0.1,
			"upper_lim": 0.1,
			"momentum": 0.7,
			"batch_size": "full",
			"lr": 0.1,
			"loss": "squared",
			"metr": "bin_class_acc",
			"epochs": 150
		},
		{
			"units_per_layer": [
				2,
				2,
				1
			],
			"acts": [
				"leaky_relu",
				"leaky_relu",
				"tanh"
			],
			"init_type": "uniform",
			"lower_lim": -0.1,
			"upper_lim": 0.1,
			"momentum": 0.7,
			"batch_size": "full",
			"lr": 0.3,
			"loss": "squared",
			"metr": "bin_class_acc",
			"epochs": 50
		},
		{
			"units_per_layer": [
				2,
				2,
				1
			],
			"acts": [
				"leaky_relu",
				"leaky_relu",
				"tanh"
			],
			"init_type": "uniform",
			"lower_lim": -0.1,
			"upper_lim": 0.1,
			"momentum": 0.7,
			"batch_size": "full",
			"lr": 0.3,
			"loss": "squared",
			"metr": "bin_class_acc",
			"epochs": 100
		},
		{
			"units_per_layer": [
				2,
				2,
				1
			],
			"acts": [
				"leaky_relu",
				"leaky_relu",
				"tanh"
			],
			"init_type": "uniform",
			"lower_lim": -0.1,
			"upper_lim": 0.1,
			"momentum": 0.7,
			"batch_size": "full",
			"lr": 0.3,
			"loss": "squared",
			"metr": "bin_class_acc",
			"epochs": 150
		}
	],
	"results": [
		[
			0.38097504206377864,
			0.08197382588098821,
			0.17633333333333334,
			0.1628919205417438
		],
		[
			0.2901357608115881,
			0.08184097693714804,
			0.3933333333333333,
			0.1440987315851338
		],
		[
			0.2833989375913967,
			0.13163207665102927,
			0.508,
			0.09260669522232183
		],
		[
			0.25678904849604073,
			0.10958292089817565,
			0.43633333333333335,
			0.06044648689359685
		],
		[
			0.20584998626788162,
			0.1207198943824616,
			0.708,
			0.15979987484350544
		],
		[
			0.12189376020342897,
			0.09296119928433223,
			0.774,
			0.0902441133814278
		],
		[
			0.5253567349296496,
			0.02891194880609523,
			0.0,
			0.0
		],
		[
			0.5083551159579186,
			0.004247861397165476,
			0.0,
			0.0
		],
		[
			0.4995783447467992,
			0.019608655575265088,
			0.0,
			0.0
		],
		[
			0.5148457652901842,
			0.017997401141893694,
			0.0,
			0.0
		],
		[
			0.4407784070460024,
			0.09474495637825733,
			0.26399999999999996,
			0.32555183919001285
		],
		[
			0.29893607122264865,
			0.19467163083465358,
			0.44800000000000006,
			0.3881443030626625
		]
	]
}